{"type":"FeatureCollection","name":"illustrations","crs":{"type":"name","properties":{"name":"urn:ogc:def:crs:OGC:1.3:CRS84"}},"features":[{"type":"Feature","properties":{"#MapScale":18000,"#Opacity":100,"#LayerName":"illustrations","#PageX":328.8939460139428,"#PageY":352.0552034605629,"#Id":2147483647,"#Name":"stade_tennis","#HorizontalScale":0.30278967748959423,"#VerticalScale":0.303956420959833,"#Rotation":298.563,"#Style":"stade_tennis","#MapX":783485.1041376508,"#MapY":5413113.125310827},"geometry":{"type":"Point","coordinates":[7.038166439268267,43.66088934501351]}},{"type":"Feature","properties":{"#MapScale":18000,"#Opacity":100,"#LayerName":"illustrations","#PageX":329.040032049917,"#PageY":348.4842114700808,"#Id":2147483647,"#Name":"stade_tennis","#HorizontalScale":0.30278967748959423,"#VerticalScale":0.303956420959833,"#Rotation":298.563,"#Style":"stade_tennis","#MapX":783487.7336862957,"#MapY":5413177.40316659},"geometry":{"type":"Point","coordinates":[7.038190060905646,43.66130706987579]}},{"type":"Feature","properties":{"#MapScale":18000,"#Opacity":100,"#LayerName":"illustrations","#PageX":327.33569496355057,"#PageY":349.39319124947673,"#Id":2147483647,"#Name":"stade_tennis","#HorizontalScale":0.30278967748959423,"#VerticalScale":0.303956420959833,"#Rotation":298.563,"#Style":"stade_tennis","#MapX":783457.0556187723,"#MapY":5413161.041530578},"geometry":{"type":"Point","coordinates":[7.037914475136211,43.6612007401866]}},{"type":"Feature","properties":{"#MapScale":18000,"#Opacity":100,"#LayerName":"illustrations","#PageX":327.28591811828295,"#PageY":346.5769104871831,"#Id":2147483647,"#Name":"stade_tennis","#HorizontalScale":0.30426521667800827,"#VerticalScale":0.30415723819509866,"#Rotation":27.919,"#Style":"stade_tennis","#MapX":783456.1596355584,"#MapY":5413211.734584248},"geometry":{"type":"Point","coordinates":[7.037906426382057,43.66153017953005]}},{"type":"Feature","properties":{"#MapScale":18000,"#Opacity":100,"#LayerName":"illustrations","#PageX":326.4418654659873,"#PageY":345.01865943679087,"#Id":2147483647,"#Name":"stade_tennis","#HorizontalScale":0.30426521667800827,"#VerticalScale":0.30415723819509866,"#Rotation":27.919,"#Style":"stade_tennis","#MapX":783440.9666878325,"#MapY":5413239.783103126},"geometry":{"type":"Point","coordinates":[7.037769945810528,43.66171245788175]}},{"type":"Feature","properties":{"#MapScale":18000,"#Opacity":100,"#LayerName":"illustrations","#PageX":328.895296315852,"#PageY":342.2110893495849,"#Id":2147483647,"#Name":"stade_tennis","#HorizontalScale":0.3041606488975684,"#VerticalScale":0.30433344282707286,"#Rotation":35.629,"#Style":"stade_tennis","#MapX":783485.1284430851,"#MapY":5413290.319364645},"geometry":{"type":"Point","coordinates":[7.038166657607698,43.66204087548238]}},{"type":"Feature","properties":{"#MapScale":18000,"#Opacity":100,"#LayerName":"illustrations","#PageX":337.44566254192637,"#PageY":355.982072174737,"#Id":2147483647,"#Name":"stade_foot","#HorizontalScale":1.1327760097780217,"#VerticalScale":1.1326058702909647,"#Rotation":292.905,"#Style":"stade_foot","#MapX":783639.0350349981,"#MapY":5413042.441674044},"geometry":{"type":"Point","coordinates":[7.039549224046119,43.660429987311545]}}]}